LICENSE
README.rst
setup.py
CVX2.egg-info/PKG-INFO
CVX2.egg-info/SOURCES.txt
CVX2.egg-info/dependency_links.txt
CVX2.egg-info/not-zip-safe
CVX2.egg-info/requires.txt
CVX2.egg-info/top_level.txt
cvx2/__init__.py
cvx2/attention.py
cvx2/convlstm.py
cvx2/do_conv.py
cvx2/utils.py
cvx2/wrapper.py
test/test.py
test/test2.py