Metadata-Version: 2.1
Name: CVX2
Version: 0.6.0
Summary: Tools of CV(Computer Vision)
Home-page: https://gitee.com/summry/cvx2
Author: summy
Author-email: fkfkfk2024@2925.com
License: UNKNOWN
Keywords: CV,Computer Vision,Machine learning,Deep learning,torch
Platform: UNKNOWN
Requires-Python: >=3.6
License-File: LICENSE
